auctus_search-0.1.0.dist-info/METADATA
auctus_search-0.1.0.dist-info/WHEEL
auctus_search-0.1.0.dist-info/entry_points.txt
auctus_search-0.1.0.dist-info/licenses/LICENSE
auctus_search/API/__init__.py
auctus_search/API/api.py
auctus_search/API/collection.py
auctus_search/API/models.py
auctus_search/__init__.py
auctus_search/__main__.py
auctus_search/auctus.py
auctus_search/components/__init__.py
auctus_search/components/dataset_card.py
auctus_search/helpers/__init__.py
auctus_search/helpers/check_dict_keys.py
auctus_search/helpers/ensure_dataset_identifier.py
auctus_search/helpers/ensure_dataset_loaded.py
auctus_search/helpers/ensure_non_empty_search_query.py
auctus_search/mixins/__init__.py
auctus_search/mixins/display.py
auctus_search/mixins/loader.py
auctus_search/mixins/profile.py
auctus_search/mixins/search.py
auctus_search/py.typed
auctus_search-0.1.0.dist-info/RECORD
