Metadata-Version: 2.4
Name: auctus-search
Version: 0.1.0
Author-Email: Provost Simon <sgp9504@nyu.edu>, New York University <fairuse@nyu.edu>
License-Expression: MIT
License-File: LICENSE
Classifier: Development Status :: 4 - Beta
Classifier: Intended Audience :: Developers
Classifier: Programming Language :: Python
Classifier: Programming Language :: Python :: 3
Classifier: Programming Language :: Python :: 3 :: Only
Classifier: Programming Language :: Python :: 3.9
Classifier: Programming Language :: Python :: 3.10
Classifier: Programming Language :: Python :: 3.11
Classifier: Programming Language :: Python :: 3.12
Classifier: Programming Language :: Python :: 3.13
Classifier: Programming Language :: Python :: 3.14
Classifier: Topic :: Documentation
Classifier: Topic :: Software Development
Classifier: Topic :: Utilities
Classifier: Typing :: Typed
Project-URL: Homepage, https://simonprovost.github.io/auctus-search
Project-URL: Changelog, https://simonprovost.github.io/auctus-search/changelog
Project-URL: Repository, https://github.com/simonprovost/auctus-search
Project-URL: Issues, https://github.com/simonprovost/auctus-search/issues
Project-URL: Discussions, https://github.com/simonprovost/auctus-search/discussions
Requires-Python: >=3.9
Requires-Dist: beartype>=0.19.0
Requires-Dist: data-profile-viewer>=0.2.7
Requires-Dist: datamart-profiler>=0.11
Requires-Dist: geopandas>=1.0.1
Requires-Dist: ipython>=8.18.1
Requires-Dist: ipywidgets>=8.1.5
Requires-Dist: millify>=0.1.1
Requires-Dist: requests>=2.32.3
Requires-Dist: ruff>=0.9.6
Requires-Dist: skrub>=0.5.1
